README.md
setup.py
mdgraph/__init__.py
mdgraph.egg-info/PKG-INFO
mdgraph.egg-info/SOURCES.txt
mdgraph.egg-info/dependency_links.txt
mdgraph.egg-info/top_level.txt